retriever_search/DocumentIngestion.py
retriever_search/QueryPipeline.py
retriever_search/Utils.py
retriever_search/__init__.py
retriever_search/dashboard.py
retriever_search/frontend_app.py
retriever_search/search_server.py
retriever_search-1.0.1.dist-info/LICENSE
retriever_search-1.0.1.dist-info/METADATA
retriever_search-1.0.1.dist-info/WHEEL
retriever_search-1.0.1.dist-info/top_level.txt
retriever_search-1.0.1.dist-info/RECORD
